xl_engine/__init__.py
xl_engine/excel_engine.py
xl_engine-0.4.0.dist-info/licenses/LICENSE
xl_engine-0.4.0.dist-info/WHEEL
xl_engine-0.4.0.dist-info/METADATA
xl_engine-0.4.0.dist-info/RECORD
