Metadata-Version: 2.4
Name: xl-engine
Version: 0.4.0
Summary: A Python package that provides convenience functions using XLWings to parametrize,
Author-email: Connor Ferster <connor@structuralpython.com>
Requires-Python: >=3.11
License-File: LICENSE
Requires-Dist: ipywidgets>=8.1.7
Requires-Dist: rich
Requires-Dist: xlwings>=0.33.15
